agent_os/enforcer.py
agent_os/sdk.py
agent_os/cli/__init__.py
agent_os/cli/api.py
agent_os/cli/config.py
agent_os/cli/main.py
agentos/__init__.py
agentos_client-0.1.0.dist-info/METADATA
agentos_client-0.1.0.dist-info/WHEEL
agentos_client-0.1.0.dist-info/entry_points.txt
agentos_client-0.1.0.dist-info/top_level.txt
agentos_client-0.1.0.dist-info/RECORD
