Metadata-Version: 2.4
Name: agentos-client
Version: 0.1.0
Summary: AgentOS SDK
Author: AgentOS
License: Proprietary
Requires-Python: >=3.11
Requires-Dist: click>=8.1
Requires-Dist: PyYAML>=6.0.1
Requires-Dist: requests>=2.31
Provides-Extra: cli
Provides-Extra: dev
Requires-Dist: pytest; extra == "dev"
Requires-Dist: ruff; extra == "dev"
Requires-Dist: black; extra == "dev"
